{
    "fluentMethods": true,
    "relationships": [],
    "fields": [
        {
            "fieldName": "note",
            "fieldType": "String"
        },
        {
            "fieldName": "statusFromDate",
            "fieldType": "ZonedDateTime",
            "fieldValidateRules": [
                "required"
            ]
        },
        {
            "fieldName": "statusChangeDate",
            "fieldType": "ZonedDateTime",
            "fieldValidateRules": [
                "required"
            ]
        }
    ],
    "changelogDate": "20180223200315",
    "entityTableName": "request_status_log",
    "dto": "no",
    "pagination": "no",
    "service": "no",
    "jpaMetamodelFiltering": false
}